shapely_geojson.py
shapely_geojson-0.0.1.dist-info/DESCRIPTION.rst
shapely_geojson-0.0.1.dist-info/METADATA
shapely_geojson-0.0.1.dist-info/RECORD
shapely_geojson-0.0.1.dist-info/WHEEL
shapely_geojson-0.0.1.dist-info/metadata.json
shapely_geojson-0.0.1.dist-info/top_level.txt
